modules/filter/biquad_filter.v
module biquad_filter #(
    parameter INOUT_WIDTH = 12,
    parameter INOUT_DECIMAL_WIDTH = 11,
    parameter COEF_WIDTH = 24,
    parameter COEF_DECIMAL_WIDTH = 23,
    parameter INTERNAL_WIDTH = 24,
    parameter INTERNAL_DECIMAL_WIDTH = 23,
    // Coefficients
    parameter signed b0 = 0,
    parameter signed b1 = 0,
    parameter signed b2 = 0,
    parameter signed a1 = 0,
    parameter signed a2 = 0
) (
    input clk,
    input reset, 

    input  [INOUT_WIDTH-1:0] din,
    output [INOUT_WIDTH-1:0] dout
);

    localparam INOUT_INTEGER_WIDTH = INOUT_WIDTH - INOUT_DECIMAL_WIDTH;
    localparam COEF_INTEGER_WIDTH = COEF_WIDTH - COEF_DECIMAL_WIDTH;
    localparam INTERNAL_INTEGER_WIDTH = INTERNAL_WIDTH - INTERNAL_DECIMAL_WIDTH;

    wire signed [INTERNAL_WIDTH-1:0] x_n_int;
    wire signed [INTERNAL_WIDTH-1:0] b0_int;
    wire signed [INTERNAL_WIDTH-1:0] b1_int;
    wire signed [INTERNAL_WIDTH-1:0] b2_int;
    wire signed [INTERNAL_WIDTH-1:0] a1_int;
    wire signed [INTERNAL_WIDTH-1:0] a2_int;
    wire signed [INTERNAL_WIDTH-1:0] y_n_int;

    // Previous values regs
    reg signed [INTERNAL_WIDTH-1:0] x_n1;
    reg signed [INTERNAL_WIDTH-1:0] x_n2;
    reg signed [INTERNAL_WIDTH-1:0] y_n1;
    reg signed [INTERNAL_WIDTH-1:0] y_n2;

    // Product values regs
    reg signed [INTERNAL_WIDTH+INTERNAL_WIDTH-1:0] product_b0; // x_{n}*b0
    reg signed [INTERNAL_WIDTH+INTERNAL_WIDTH-1:0] product_b1; // x_{n-1}*b1  
    reg signed [INTERNAL_WIDTH+INTERNAL_WIDTH-1:0] product_b2; // x_{n-2}*b2
    reg signed [INTERNAL_WIDTH+INTERNAL_WIDTH-1:0] product_a1; // y_{n-1}*a1
    reg signed [INTERNAL_WIDTH+INTERNAL_WIDTH-1:0] product_a2; // y_{n-2}*a2
    wire signed [INTERNAL_WIDTH+INTERNAL_WIDTH-1:0] y_n_add;   // sum(product_*)

    // Resize
    assign x_n_int = { {(INTERNAL_INTEGER_WIDTH-INOUT_INTEGER_WIDTH){din[INOUT_WIDTH-1]}}, din, {(INTERNAL_DECIMAL_WIDTH-INOUT_DECIMAL_WIDTH){1'b0}} };
    assign b0_int  = { {(INTERNAL_INTEGER_WIDTH-COEF_INTEGER_WIDTH){b0[COEF_WIDTH-1]}}, b0, {(INTERNAL_DECIMAL_WIDTH-COEF_DECIMAL_WIDTH){1'b0}} };
    assign b1_int  = { {(INTERNAL_INTEGER_WIDTH-COEF_INTEGER_WIDTH){b1[COEF_WIDTH-1]}}, b1, {(INTERNAL_DECIMAL_WIDTH-COEF_DECIMAL_WIDTH){1'b0}} };
    assign b2_int  = { {(INTERNAL_INTEGER_WIDTH-COEF_INTEGER_WIDTH){b2[COEF_WIDTH-1]}}, b2, {(INTERNAL_DECIMAL_WIDTH-COEF_DECIMAL_WIDTH){1'b0}} };
    assign a1_int  = { {(INTERNAL_INTEGER_WIDTH-COEF_INTEGER_WIDTH){a1[COEF_WIDTH-1]}}, a1, {(INTERNAL_DECIMAL_WIDTH-COEF_DECIMAL_WIDTH){1'b0}} };
    assign a2_int  = { {(INTERNAL_INTEGER_WIDTH-COEF_INTEGER_WIDTH){a2[COEF_WIDTH-1]}}, a2, {(INTERNAL_DECIMAL_WIDTH-COEF_DECIMAL_WIDTH){1'b0}} };

    // Saving previous values
    always @(posedge clk) begin
        if (reset) begin
            x_n1 <= 0;
            x_n2 <= 0;
            y_n1 <= 0;
            y_n2 <= 0;
        end else begin
            x_n2 <= x_n1;
            x_n1 <= x_n_int;
            y_n2 <= y_n1;
            y_n1 <= y_n_int;
        end
    end

    //Computing multiplications
    always @(posedge clk) begin
        if (reset) begin
            product_b0 <= 0;
            product_b1 <= 0;
            product_b2 <= 0;
            product_a1 <= 0;
            product_a2 <= 0;
        end else begin
            product_b0 <= b0 * x_n_int;
            product_b1 <= b1 * x_n1;
            product_b2 <= b2 * x_n2;
            product_a1 <= a1 * y_n1;
            product_a2 <= a2 * y_n2;
        end
    end
    // Add the biquad formula, though it still has 2*INTERNAL_SIZE bits because of multiplication
    assign y_n_add = product_b0 + product_b1 + product_b2 + product_a1 + product_a2;
    // Truncate to internal size
    assign y_n_int = y_n_add >>> (INTERNAL_DECIMAL_WIDTH);
    // Lastly put INOUT_WIDTH bits on output
    assign dout = y_n_int >>> (INTERNAL_DECIMAL_WIDTH-INOUT_DECIMAL_WIDTH)    ;
endmodule

modules/filter/biquad_filter_tb.v
module biquad_filter_tb;
  reg clk;
  reg reset;
  reg  [15:0] din;
  wire [15:0] dout;

  // Instantiate the biquad_filter module
  biquad_filter #(
    .INOUT_WIDTH(16),
    .INOUT_DECIMAL_WIDTH(14),
    .COEF_WIDTH(24),
    .COEF_DECIMAL_WIDTH(22),
    .INTERNAL_WIDTH(24),
    .INTERNAL_DECIMAL_WIDTH(22),
    .b0(24'h400000),  //   1    0x400000
    .b1(24'hc00000),  //  -1    0xc00000
    .b2(24'h000000),  // 0
    .a1(24'h000000),  // 0
    .a2(24'h000000)   // 0
  ) dut (
    .clk(clk),
    .reset(reset),
    .din(din),
    .dout(dout)
  );

  // Clock generation
  always begin
    #5 clk = ~clk;
  end

  // Initialize signals
  initial begin
    $dumpfile("biquad_filter_tb.vcd");
	  $dumpvars(0,biquad_filter_tb); 

    clk = 0;
    reset = 0;
    din = 0;

    // Apply reset
    #10 reset = 1;

    // Wait for a few clock cycles
    #20 reset = 0;

    // Apply input values and observe outputs
    din = 16'hc000;

    // Stop simulation
    #200000 $finish;
  end

endmodule

modules/filter/biquad_filter_tb.vcd
$date
	Mon Jun 26 08:04:31 2023
$end
$version
	Icarus Verilog
$end
$timescale
	1s
$end
$scope module biquad_filter_tb $end
$var wire 16 ! dout [15:0] $end
$var reg 1 " clk $end
$var reg 16 # din [15:0] $end
$var reg 1 $ reset $end
$scope module dut $end
$var wire 24 % a1_int [23:0] $end
$var wire 24 & a2_int [23:0] $end
$var wire 24 ' b0_int [23:0] $end
$var wire 24 ( b1_int [23:0] $end
$var wire 24 ) b2_int [23:0] $end
$var wire 1 " clk $end
$var wire 16 * din [15:0] $end
$var wire 1 $ reset $end
$var wire 24 + y_n_int [23:0] $end
$var wire 48 , y_n_add [47:0] $end
$var wire 24 - x_n_int [23:0] $end
$var wire 16 . dout [15:0] $end
$var parameter 32 / COEF_DECIMAL_WIDTH $end
$var parameter 33 0 COEF_INTEGER_WIDTH $end
$var parameter 32 1 COEF_WIDTH $end
$var parameter 32 2 INOUT_DECIMAL_WIDTH $end
$var parameter 33 3 INOUT_INTEGER_WIDTH $end
$var parameter 32 4 INOUT_WIDTH $end
$var parameter 32 5 INTERNAL_DECIMAL_WIDTH $end
$var parameter 33 6 INTERNAL_INTEGER_WIDTH $end
$var parameter 32 7 INTERNAL_WIDTH $end
$var parameter 24 8 a1 $end
$var parameter 24 9 a2 $end
$var parameter 24 : b0 $end
$var parameter 24 ; b1 $end
$var parameter 24 < b2 $end
$var reg 48 = product_a1 [47:0] $end
$var reg 48 > product_a2 [47:0] $end
$var reg 48 ? product_b0 [47:0] $end
$var reg 48 @ product_b1 [47:0] $end
$var reg 48 A product_b2 [47:0] $end
$var reg 24 B x_n1 [23:0] $end
$var reg 24 C x_n2 [23:0] $end
$var reg 24 D y_n1 [23:0] $end
$var reg 24 E y_n2 [23:0] $end
$upscope $end
$upscope $end
$enddefinitions $end
$comment Show the parameter values. $end
$dumpall
b0 <
b110000000000000000000000 ;
b10000000000000000000000 :
b0 9
b0 8
b11000 7
b10 6
b10110 5
b10000 4
b10 3
b1110 2
b11000 1
b10 0
b10110 /
$end
#0
$dumpvars
bx E
bx D
bx C
bx B
bx A
bx @
bx ?
bx >
bx =
bx .
b0 -
bx ,
bx +
b0 *
b0 )
b110000000000000000000000 (
b10000000000000000000000 '
b0 &
b0 %
0$
b0 #
0"
bx !
$end
#5
b0 B
b0 ?
1"
#10
0"
1$
#15
b0 !
b0 .
b0 +
b0 ,
b0 >
b0 =
b0 A
b0 @
b0 E
b0 D
b0 C
1"
#20
0"
#25
1"
#30
0"
b110000000000000000000000 -
b1100000000000000 #
b1100000000000000 *
0$
#35
b1100000000000000 !
b1100000000000000 .
b110000000000000000000000 +
b111100000000000000000000000000000000000000000000 ,
b111100000000000000000000000000000000000000000000 ?
b110000000000000000000000 B
1"
#40
0"
#45
b0 !
b0 .
b0 +
b110000000000000000000000 D
b110000000000000000000000 C
b0 ,
b100000000000000000000000000000000000000000000 @
1"
#50
0"
#55
b0 D
b110000000000000000000000 E
1"
#60
0"
#65
b0 E
1"
